pyssub/__init__.py
pyssub/sbatch.py
pyssub/scmd.py
pyssub/shist.py
pyssub-0.1.data/scripts/ssub
pyssub-0.1.dist-info/LICENSE
pyssub-0.1.dist-info/METADATA
pyssub-0.1.dist-info/WHEEL
pyssub-0.1.dist-info/top_level.txt
pyssub-0.1.dist-info/RECORD
