Metadata-Version: 2.1
Name: pyssub
Version: 0.1
Summary: Slurm job submission in Python
Home-page: https://github.com/kkrings/pyssub/
Author: Kai Krings
Author-email: kai.krings@posteo.de
License: GPLv3
Project-URL: Documentation, https://pyssub.readthedocs.io/
Project-URL: Source, https://github.com/kkrings/pyssub/
Project-URL: Tracker, https://github.com/kkrings/pyssub/issues/
Platform: UNKNOWN
Classifier: Development Status :: 4 - Beta
Classifier: Intended Audience :: Science/Research
Classifier: License :: OSI Approved :: GNU General Public License v3 (GPLv3)
Classifier: Operating System :: Unix
Classifier: Programming Language :: Python :: 3.6
Classifier: Topic :: Scientific/Engineering
Requires-Python: >=3.6
